{
    "code": "custom-css",
    "type": "E",
    "filepath": "https://fonts.googleapis.com/css2?family=Lora:ital@0;1&family=Raleway:ital,wght@0,400;0,500;0,700;0,800;1,400;1,700;1,800&display=swap",
    "is_global": true,
    "active": false,
    "attributes": [
        {
            "name": "type",
            "value": "text/css"
        },
        {
            "name": "media",
            "value": "all"
        },
        {
            "name": "rel",
            "value": "stylesheet"
        }
    ]
}